odoo/addons/sign_oca/README.rst
odoo/addons/sign_oca/__init__.py
odoo/addons/sign_oca/__manifest__.py
odoo/addons/sign_oca/controllers/__init__.py
odoo/addons/sign_oca/controllers/main.py
odoo/addons/sign_oca/data/data.xml
odoo/addons/sign_oca/data/ir_sequence_data.xml
odoo/addons/sign_oca/demo/sign_oca_template.xml
odoo/addons/sign_oca/i18n/es.po
odoo/addons/sign_oca/i18n/fr.po
odoo/addons/sign_oca/i18n/fr_FR.po
odoo/addons/sign_oca/i18n/it.po
odoo/addons/sign_oca/i18n/pt_BR.po
odoo/addons/sign_oca/i18n/sign_oca.pot
odoo/addons/sign_oca/i18n/sv.po
odoo/addons/sign_oca/migrations/18.0.1.2.0/pre-migration.py
odoo/addons/sign_oca/models/__init__.py
odoo/addons/sign_oca/models/res_company.py
odoo/addons/sign_oca/models/res_partner.py
odoo/addons/sign_oca/models/res_users.py
odoo/addons/sign_oca/models/sign_oca_field.py
odoo/addons/sign_oca/models/sign_oca_request.py
odoo/addons/sign_oca/models/sign_oca_role.py
odoo/addons/sign_oca/models/sign_oca_template.py
odoo/addons/sign_oca/readme/CONFIGURE.md
odoo/addons/sign_oca/readme/CONTRIBUTORS.md
odoo/addons/sign_oca/readme/DESCRIPTION.md
odoo/addons/sign_oca/readme/ROADMAP.md
odoo/addons/sign_oca/readme/USAGE.md
odoo/addons/sign_oca/reports/signature_certificate.xml
odoo/addons/sign_oca/reports/signature_certificate_report.xml
odoo/addons/sign_oca/security/ir.model.access.csv
odoo/addons/sign_oca/security/security.xml
odoo/addons/sign_oca/static/description/icon.png
odoo/addons/sign_oca/static/description/icon.svg
odoo/addons/sign_oca/static/description/index.html
odoo/addons/sign_oca/static/src/components/sign_oca_configure/sign_oca_configure.esm.js
odoo/addons/sign_oca/static/src/components/sign_oca_configure/sign_oca_configure.xml
odoo/addons/sign_oca/static/src/components/sign_oca_configure/sign_oca_configure_field_dialog.esm.js
odoo/addons/sign_oca/static/src/components/sign_oca_configure/sign_oca_configure_field_dialog.xml
odoo/addons/sign_oca/static/src/components/sign_oca_pdf/sign_oca_pdf.esm.js
odoo_addon_sign_oca-18.0.1.4.2.2.dist-info/METADATA
odoo_addon_sign_oca-18.0.1.4.2.2.dist-info/WHEEL
odoo_addon_sign_oca-18.0.1.4.2.2.dist-info/top_level.txt
odoo_addon_sign_oca-18.0.1.4.2.2.dist-info/RECORD
