Metadata-Version: 2.1
Name: odoo-addon-sign_oca
Version: 18.0.1.4.2.2
Requires-Python: >=3.10
Requires-Dist: odoo==18.0.*
Summary: Allow to sign documents inside Odoo CE
Home-page: https://github.com/OCA/sign
License: AGPL-3
Author: Dixmit,Odoo Community Association (OCA)
Author-email: support@odoo-community.org
Classifier: Programming Language :: Python
Classifier: Framework :: Odoo
Classifier: Framework :: Odoo :: 18.0
Classifier: License :: OSI Approved :: GNU Affero General Public License v3
